pathologyfoundation/__init__.py
pathologyfoundation/model_zoo.py
pathologyfoundation/utils.py
pathologyfoundation/dataset/__init__.py
pathologyfoundation/dataset/load_data.py
pathologyfoundation/models/__init__.py
pathologyfoundation/models/finetuner.py
pathologyfoundation/models/plip_vit.py
pathologyfoundation-0.2.7.dist-info/LICENSE
pathologyfoundation-0.2.7.dist-info/METADATA
pathologyfoundation-0.2.7.dist-info/WHEEL
pathologyfoundation-0.2.7.dist-info/top_level.txt
pathologyfoundation-0.2.7.dist-info/RECORD
